marshy_config_persisty_data/__init__.py
marshy_config_persisty_data/bytes_marshaller.py
persisty_data/__init__.py
persisty_data/file_handle.py
persisty_data/file_store_abc.py
persisty_data/file_store_actions.py
persisty_data/file_store_meta.py
persisty_data/has_url.py
persisty_data/routes.py
persisty_data/stored_file_handle.py
persisty_data/upload_handle.py
persisty_data/upload_part.py
persisty_data/directory/__init__.py
persisty_data/directory/directory_file_handle_writer.py
persisty_data/directory/directory_file_store.py
persisty_data/finder/__init__.py
persisty_data/finder/file_store_action_finder.py
persisty_data/finder/file_store_finder_abc.py
persisty_data/finder/file_store_route_factory.py
persisty_data/finder/file_store_store_meta_finder.py
persisty_data/finder/module_file_store_finder.py
persisty_data/generator/__init__.py
persisty_data/generator/content_type_generator.py
persisty_data/generator/file_handle_id_generator.py
persisty_data/generator/future_timestamp_generator.py
persisty_data/generator/part_number_generator.py
persisty_data/generator/pattern_generator.py
persisty_data/generator/upload_url_generator.py
persisty_data/img/__init__.py
persisty_data/img/img_resize_action.py
persisty_data/img/img_resizer.py
persisty_data/persisty_store/__init__.py
persisty_data/persisty_store/data_chunk.py
persisty_data/persisty_store/data_chunk_reader.py
persisty_data/persisty_store/data_chunk_writer.py
persisty_data/persisty_store/persisty_file_handle.py
persisty_data/persisty_store/persisty_file_handle_writer.py
persisty_data/persisty_store/persisty_file_store.py
persisty_data/persisty_store/persisty_file_store_abc.py
persisty_data/persisty_store/persisty_upload_handle.py
persisty_data/persisty_store/persisty_upload_part.py
persisty_data/s3/__init__.py
persisty_data/s3/s3_client.py
persisty_data/s3/s3_content_writer.py
persisty_data/s3/s3_file_store.py
persisty_data/s3/s3_upload_part_writer.py
persisty_data/s3/s3_yml_config.py
persisty_data/security/__init__.py
persisty_data-0.0.3.dist-info/METADATA
persisty_data-0.0.3.dist-info/WHEEL
persisty_data-0.0.3.dist-info/top_level.txt
persisty_data-0.0.3.dist-info/RECORD
