Metadata-Version: 2.1
Name: persisty-data
Version: 0.0.3
Summary: A binary data persistence layer built on top of persisty
Home-page: https://github.com/tofarr/persisty-data
Author: Tim O'Farrell
Author-email: tofarr@gmail.com
Classifier: Programming Language :: Python :: 3
Classifier: License :: OSI Approved :: MIT License
Classifier: Operating System :: OS Independent
Requires-Dist: persisty[all]
Provides-Extra: all
Requires-Dist: pytest ~=7.2 ; extra == 'all'
Requires-Dist: pytest-cov ~=4.0 ; extra == 'all'
Requires-Dist: pytest-xdist ~=3.2 ; extra == 'all'
Requires-Dist: moto ~=3.1 ; extra == 'all'
Requires-Dist: black ~=23.3 ; extra == 'all'
Requires-Dist: boto3 ~=1.26 ; extra == 'all'
Requires-Dist: Pillow ~=10.0 ; extra == 'all'
Requires-Dist: pylint ~=3.0 ; extra == 'all'
Provides-Extra: dev
Requires-Dist: black ~=23.3 ; extra == 'dev'
Requires-Dist: pytest ~=7.2 ; extra == 'dev'
Requires-Dist: pytest-cov ~=4.0 ; extra == 'dev'
Requires-Dist: pytest-xdist ~=3.2 ; extra == 'dev'
Requires-Dist: pylint ~=3.0 ; extra == 'dev'
Requires-Dist: boto3 ~=1.26 ; extra == 'dev'
Requires-Dist: moto ~=3.1 ; extra == 'dev'
Provides-Extra: img
Requires-Dist: Pillow ~=10.0 ; extra == 'img'
